MoguiYuehuixueVer2/README.md
MoguiYuehuixueVer2/__init__.py
MoguiYuehuixueVer2/__main__.py
MoguiYuehuixueVer2/file.epub
MoguiYuehuixueVer2/index.html
MoguiYuehuixueVer2/css/__init__.py
MoguiYuehuixueVer2/css/annotations.css
MoguiYuehuixueVer2/css/main.css
MoguiYuehuixueVer2/css/normalize.css
MoguiYuehuixueVer2/css/popup.css
MoguiYuehuixueVer2/font/__init__.py
MoguiYuehuixueVer2/font/fontello.eot
MoguiYuehuixueVer2/font/fontello.svg
MoguiYuehuixueVer2/font/fontello.ttf
MoguiYuehuixueVer2/font/fontello.woff
MoguiYuehuixueVer2/img/__init__.py
MoguiYuehuixueVer2/img/annotator-glyph-sprite.png
MoguiYuehuixueVer2/img/annotator-icon-sprite.png
MoguiYuehuixueVer2/img/apple-touch-icon.png
MoguiYuehuixueVer2/img/cancelfullscreen.png
MoguiYuehuixueVer2/img/close.png
MoguiYuehuixueVer2/img/fullscreen.png
MoguiYuehuixueVer2/img/loader.gif
MoguiYuehuixueVer2/img/menu-icon.png
MoguiYuehuixueVer2/img/save.png
MoguiYuehuixueVer2/img/saved.png
MoguiYuehuixueVer2/img/settings-s.png
MoguiYuehuixueVer2/img/settings.png
MoguiYuehuixueVer2/img/star.png
MoguiYuehuixueVer2/js/__init__.py
MoguiYuehuixueVer2/js/epub.js
MoguiYuehuixueVer2/js/epub.min.js
MoguiYuehuixueVer2/js/epub.min.map
MoguiYuehuixueVer2/js/hooks.min.js
MoguiYuehuixueVer2/js/hooks.min.map
MoguiYuehuixueVer2/js/reader.js
MoguiYuehuixueVer2/js/reader.js.map
MoguiYuehuixueVer2/js/reader.min.js
MoguiYuehuixueVer2/js/reader.min.map
MoguiYuehuixueVer2/js/hooks/__init__.py
MoguiYuehuixueVer2/js/hooks/extensions/__init__.py
MoguiYuehuixueVer2/js/hooks/extensions/highlight.js
MoguiYuehuixueVer2/js/libs/__init__.py
MoguiYuehuixueVer2/js/libs/jquery.min.js
MoguiYuehuixueVer2/js/libs/localforage.min.js
MoguiYuehuixueVer2/js/libs/screenfull.js
MoguiYuehuixueVer2/js/libs/screenfull.min.js
MoguiYuehuixueVer2/js/libs/zip.min.js
MoguiYuehuixueVer2/js/plugins/__init__.py
MoguiYuehuixueVer2/js/plugins/hypothesis.js
MoguiYuehuixueVer2/js/plugins/search.js
mogui_yuehuixue_ver2-2022.10.11.0.dist-info/METADATA
mogui_yuehuixue_ver2-2022.10.11.0.dist-info/WHEEL
mogui_yuehuixue_ver2-2022.10.11.0.dist-info/entry_points.txt
mogui_yuehuixue_ver2-2022.10.11.0.dist-info/top_level.txt
mogui_yuehuixue_ver2-2022.10.11.0.dist-info/RECORD
